{
    "items": [
        {
            "id": 1,
            "date": "2019-12-31",
            "description": "Recebimento de TED",
            "amount": 200.00,
            "balance": {
                "before": 1965.09,
                "after": 2216.08
            }
        },
        {
            "id": 2,
            "date": "2019-12-30",
            "description": "Pagamento da conta de gás",
            "amount": -50.99,
            "balance": {
                "before": 2016.08,
                "after": 1965.09
            }
        },
        {
            "id": 3,
            "date": "2019-11-29",
            "description": "Pagamento da conta de energia",
            "amount": -85.09,
            "balance": {
                "before": 2101.17,
                "after": 2016.08
            }
        },
        {
            "id": 4,
            "date": "2019-10-12",
            "description": "Recebimento de TED",
            "amount": 1000.00,
            "balance": {
                "before": 1101.17,
                "after": 2101.17
            }
        },
        {
            "id": 5,
            "date": "2019-09-05",
            "description": "Posto de gasolina Tiago Rocha's",
            "amount": -24.00,
            "balance": {
                "before": 1125.17,
                "after": 1101.17
            }
        },
        {
            "id": 6,
            "date": "2019-08-15",
            "description": "Mercado Verde",
            "amount": -150.00,
            "balance": {
                "before": 1275.17,
                "after": 1125.17
            }
        },
        {
            "id": 7,
            "date": "2019-07-03",
            "description": "Sorveteria Lilos",
            "amount": -48.90,
            "balance": {
                "before": 1324.07,
                "after": 1275.17
            }
        }
    ],
    "paging": {
        "totalItems": 7,
        "currentPage": 1,
        "pageSize": 7,
        "pageCount": 1
    }
}